[
    {
        "id": 1,
        "idKeeper": "2",
        "idOwner": 1,
        "state": "accepted",
        "date": "2022-10-30",
        "pets": []
    },
    {
        "id": 2,
        "idKeeper": "2",
        "idOwner": 1,
        "state": "earring",
        "date": "2022-10-23",
        "pets": [
            "1",
            "1",
            "4"
        ]
    },
    {
        "id": 4,
        "idKeeper": "2",
        "idOwner": 1,
        "state": "accepted",
        "date": "2022-11-17",
        "pets": [
            "1"
        ]
    },
    {
        "id": 3,
        "idKeeper": "2",
        "idOwner": 1,
        "state": "refused",
        "date": "2022-10-30",
        "pets": [
            "1"
        ]
    }
]